{
    "title": "举报superqiu(UID: 1779771) 在服务端插件版违反混淆相关版规",
    "author": "William_Shi",
    "replyCount": 2,
    "timestamp": 1589348160,
    "txt_content": " 本帖最后由 William_Shi 于 2020-5-13 14:07 编辑 \n\n我在莫老的BK开发群看到了此人的相关行为，故在此实锤此人违反服务端插件版相关版规的行为\n（在此人插件原帖下刚刚已有实锤，大体与我说的差不多）\n\n这是服务端插件版版规\nhttps://www.mcbbs.net/thread-535436-1-1.html\n\n\n现开始要求原创插件只能有基本的混淆(例如mojang对mc代码的混淆一样)\n只允许对[包名, 类名, 方法名, 参数名, 变量名]进行混淆\n未提到的内容不允许混淆(如字符串, 类内容, 方法内容)\n此外不允许对包名根目录以及插件主类名字进行混淆\n如\ncom.example.myplugin.MyPlugin\n复制代码\n是可以的\n但是\na.a.a.a.acom.example.myplugin.a.a.a.MyPlugina.a.a.a.Main\n\n是不允许的\n从2020年3月5日起新申请的关于原创插件的任何申请(包括原创奖励)\n若没有按照新内容要求执行 插件版将不处理申请\n\n注: kotlin或scala这类jvm语言编译的本身不太可读的字节码不算做混淆范围\n(2020/3/5)\n这是涉嫌违规的帖子\nhttps://www.mcbbs.net/thread-1044195-1-1.html\n\n\n最初是Mical为了学习PAPI，反编译了该插件，我刚刚也经过反编译确认了\n现在贴出其违反版规部分内容\n\n\nplugin.yml中的主类包名和类名如下 \nname: EzScoreBoard\nauthor: Yeoc\nversion: 1.0.0\ndepend:\n  - PlaceholderAPI\nmain: l.l.l.l.E\n主类名为 I.I.I.I.E，不会编程的坛友应该也能看懂吧，包名与类名进行了混淆，违反版规\n其他类使用了大量L和i（小写L大写i）命名的方法、参数不算违规，但是这一段是违规的\n\n\n private static String lIlllIl(boolean llllIIllllIIlll, boolean llllIIllllIIllI) {\n    // Byte code:\n    //   0: new java/lang/String\n    //   3: dup\n    //   4: invokestatic getDecoder : ()Ljava/util/Base64$Decoder;\n    //   7: aload_0\n    //   8: getstatic java/nio/charset/StandardCharsets.UTF_8 : Ljava/nio/charset/Charset;\n    //   11: invokevirtual getBytes : (Ljava/nio/charset/Charset;)[B\n    //   14: invokevirtual decode : ([B)[B\n    //   17: getstatic java/nio/charset/StandardCharsets.UTF_8 : Ljava/nio/charset/Charset;\n    //   20: invokespecial <init> : ([BLjava/nio/charset/Charset;)V\n    //   23: astore_0\n    //   24: new java/lang/StringBuilder\n    //   27: dup\n    //   28: invokespecial <init> : ()V\n    //   31: astore_2\n    //   32: aload_1\n    //   33: invokevirtual toCharArray : ()[C\n    //   36: astore_3\n    //   37: getstatic l/l/l/l/f.lIIIl : [I\n    //   40: iconst_0\n    //   41: iaload\n    //   42: istore #4\n    //   44: aload_0\n    //   45: invokevirtual toCharArray : ()[C\n    //   48: astore #5\n    //   50: aload #5\n    //   52: arraylength\n    //   53: istore #6\n    //   55: getstatic l/l/l/l/f.lIIIl : [I\n    //   58: iconst_0\n    //   59: iaload\n    //   60: istore #7\n    //   62: iload #7\n    //   64: iload #6\n    //   66: invokestatic lllIIII : (II)Z\n    //   69: ifeq -> 124\n    //   72: aload #5\n    //   74: iload #7\n    //   76: caload\n    //   77: istore #8\n    //   79: aload_2\n    //   80: iload #8\n    //   82: aload_3\n    //   83: iload #4\n    //   85: aload_3\n    //   86: arraylength\n    //   87: irem\n    //   88: caload\n    //   89: ixor\n    //   90: i2c\n    //   91: invokevirtual append : (C)Ljava/lang/StringBuilder;\n    //   94: ldc_w ''\n    //   97: invokevirtual length : ()I\n    //   100: pop2\n    //   101: iinc #4, 1\n    //   104: iinc #7, 1\n    //   107: ldc_w ''\n    //   110: invokevirtual length : ()I\n    //   113: pop\n    //   114: bipush #12\n    //   116: bipush #8\n    //   118: ixor\n    //   119: ifne -> 62\n    //   122: aconst_null\n    //   123: areturn\n    //   124: aload_2\n    //   125: invokestatic valueOf : (Ljava/lang/Object;)Ljava/lang/String;\n    //   128: areturn\n    // Local variable table:\n    //   start        length        slot        name        descriptor\n    //   44        85        4        llllIIllllIlIII        I\n    //   0        129        4        llllIIllllIIIll        J\n    //   0        129        3        llllIIllllIIlII        C\n    //   0        129        2        llllIIllllIIlIl        S\n    //   0        129        5        llllIIllllIIIlI        Ljava/lang/String;\n    //   37        92        3        llllIIllllIlIIl        [C\n    //   0        129        0        llllIIllllIllII        Ljava/lang/String;\n    //   79        25        8        llllIIllllIllIl        C\n    //   32        97        2        llllIIllllIlIlI        Ljava/lang/StringBuilder;\n    //   0        129        8        llllIIlllIlllll        J\n    //   0        129        6        llllIIllllIIIIl        Ljava/lang/String;\n    //   0        129        1        llllIIllllIlIll        Ljava/lang/String;\n    //   0        129        1        llllIIllllIIllI        Z\n    //   0        129        0        llllIIllllIIlll        Z\n    //   0        129        7        llllIIllllIIIII        Ljava/lang/String;\n  }\n具体可自行反编译查看\n而且如果使用java decompiler gui 无法反编译其主类（E.class文件）\n会报错internal error\n我暂未使用idea进行反编译\n\n\n\n\n\n8(2~HD(2KG2(TZHS1`L}YJ4.png (5.15 KB, 下载次数: 0)\n\n下载附件\n\n2020-5-13 14:04 上传\n\n\n\n\n\n\n\n\nYRS3`KIDK`C{FNS$H)BJ0XW.png (58.6 KB, 下载次数: 0)\n\n下载附件\n\n2020-5-13 14:04 上传\n\n\n\n\n\nFernFlower和jd gui都无法正常反编译此插件\n如果有大佬会做逆向工程的，可以试试看\n我无力反编译得到其源代码，虽然不能证明其主类是否存在包括但不限于含有后门等违规代码，因为无法查看源代码，但按照服务端插件版版主黑的解释，不禁止深度混淆插件发布而只是无法申请奖励，故现在不再继续举报\n\n\n\n",
    "replies": [
        {
            "author": "黑",
            "timestamp": 1589348400,
            "txt_content": "从2020年3月5日起新申请的关于原创插件的任何申请(包括原创奖励)\n若没有按照新内容要求执行 插件版将不处理申请复制代码\n\n混淆插件仅没有原创奖励，并非不允许发布。"
        },
        {
            "author": "William_Shi",
            "timestamp": 1589348760,
            "txt_content": "黑 发表于 2020-5-13 13:40\n混淆插件仅没有原创奖励，并非不允许发布。\n感谢版主大大提醒\n"
        }
    ]
}